[
  {
    "id": 1,
    "productosComprados": [
      {
        "id": 1,
        "title": "Fjallraven - Mochila Foldsack No. 1, con capacidad para 15 portátiles",
        "price": 109.95,
        "description": "Tu mochila perfecta para el uso diario y los paseos por el bosque. Guarde su computadora portátil (hasta 15 pulgadas) en la funda acolchada, su uso diario",
        "category": "Ropa de Hombre",
        "image": "https://fakestoreapi.com/img/81fPKd-2AYL._AC_SL1500_.jpg",
        "cantidad": 1
      }
    ],
    "fecha": "2024-04-26T00:28:40.738Z"
  },
  {
    "id": 1,
    "productosComprados": [
      {
        "id": 4,
        "title": "Corte ajustado informal para hombre",
        "price": 15.99,
        "description": "El color puede ser ligeramente diferente en la pantalla y en la práctica. / Tenga en cuenta que la constitución corporal varía según la persona, por lo tanto, la información detallada sobre el tamaño debe revisarse a continuación en la descripción del producto.",
        "category": "Ropa de Hombre",
        "image": "https://fakestoreapi.com/img/71YXzeOuslL._AC_UY879_.jpg",
        "cantidad": 1
      },
      {
        "id": 3,
        "title": "Chaqueta de algodón para hombre",
        "price": 55.99,
        "description": "Excelentes chaquetas de abrigo para primavera/otoño/invierno, adecuadas para muchas ocasiones, como trabajar, hacer caminatas, acampar, escalar montañas/rocas, andar en bicicleta, viajar u otras actividades al aire libre. Buena opción de regalo para usted o su familiar. Un amor de corazón cálido para el padre, esposo o hijo en este día de acción de gracias o Navidad.",
        "category": "Ropa de Hombre",
        "image": "https://fakestoreapi.com/img/71li-ujtlUL._AC_UX679_.jpg",
        "cantidad": 1
      }
    ],
    "fecha": "2024-04-26T00:29:51.313Z"
  }
]